IsoOCR/CharModel.py
IsoOCR/CharPredictor.py
IsoOCR/__init__.py
IsoOCR/modelForBoxes.py
IsoOCR/ocr.py
IsoOCR/utils.py
IsoOCR-0.0.1.dist-info/METADATA
IsoOCR-0.0.1.dist-info/WHEEL
IsoOCR-0.0.1.dist-info/top_level.txt
IsoOCR-0.0.1.dist-info/RECORD
